prboard/__init__.py
prboard/__init__.pyc
prboard/constants.py
prboard/constants.pyc
prboard/filters.py
prboard/filters.pyc
prboard/hub.py
prboard/hub.pyc
prboard/main.py
prboard/settings.py
prboard/settings.pyc
prboard/utils.py
prboard/utils.pyc
prboard/tests/__init__.py
prboard/tests/__init__.pyc
prboard/tests/integration/__init__.py
prboard/tests/integration/__init__.pyc
prboard/tests/unit/__init__.py
prboard/tests/unit/__init__.pyc
prboard/tests/unit/test_filters.py
prboard/tests/unit/test_filters.pyc
prboard/tests/unit/test_hub.py
prboard/tests/unit/test_hub.pyc
prboard/tests/unit/test_utils.py
prboard/tests/unit/test_utils.pyc
prboard-1.0a.dist-info/DESCRIPTION.rst
prboard-1.0a.dist-info/METADATA
prboard-1.0a.dist-info/RECORD
prboard-1.0a.dist-info/WHEEL
prboard-1.0a.dist-info/entry_points.txt
prboard-1.0a.dist-info/metadata.json
prboard-1.0a.dist-info/top_level.txt
