Metadata-Version: 2.0
Name: prboard
Version: 1.0a
Summary: Command line pull request dashboard for Github
Home-page: https://github.com/kumarvaradarajulu/prboard
Author: Kumar Varadarajulu
Author-email: kumarvaradarajulu@gmail.com
License: UNKNOWN
Download-URL: https://github.com/kumarvaradarajulu/prboard/tag/v1.0a
Platform: UNKNOWN
Requires-Dist: PyGithub
Requires-Dist: argparse
Requires-Dist: coverage
Requires-Dist: mock
Requires-Dist: nose
Requires-Dist: six
